Workbook

Sheet Start Here
A1: TRAP JOURNAL
A3: THE DEAL
A4: Seventeen cells per trade you take. Five per trade you skip. Under 90 seconds either way.
A5: If it ever takes longer than that, something is wrong with the sheet, not with you. Tell me and I will cut it.
A7: SET UP ONCE
A8: Dashboard cell B4: your real starting equity.
A9: Dashboard cell D5: your fee rate per side. 0.020 maker, 0.055 taker. Fees are applied automatically.
A10: Trade Log row 4: clear the example row.
A11: Playbook: edit the four setups in your own words until you would actually obey them.
A13: THE THREE ORANGE COLUMNS
A14: Pen. ATR, Candles to reclaim, and OI confirmed are the only fields that are not standard.
A15: They exist because every threshold in your checklist is currently a guess, not your finding.
... A32: A losing trade with perfect execution is a good trade. Grade the process.

Sheet Dashboard
A1: DASHBOARD
A3: Starting equity | D3: Fee rate % per side
A4: -> | B4: 50000 | D4: applied automatically to both sides
D5: 0.055 | E5: maker 0.020 / taker 0.055
A7: EXPECTANCY | D7: NET P&L | G7: WIN RATE | J7: PROFIT FACTOR | M7: RULE ADHERENCE
A8: =IFERROR(AVERAGEIFS('Trade Log'!$T$4:$T$153,'Trade Log'!$G$4:$G$153,"Yes",'Trade Log'!$T$4:$T$153,"<>"),0) -> 1.7552628 | D8: =SUMIFS('Trade Log'!$S$4:$S$153,'Trade Log'!$G$4:$G$153,"Yes") -> 875.52508 | G8: =IFERROR(COUNTIFS('Trade Log'!$G$4:$G$153,"Yes",'Trade Log'!$T$4:$T$153,">0")/COUNTIFS('Trade Log'!$G$4:$G$153,"Yes",'Trade Log'!$T$4:$T$153,"<>"),0) -> 1 | J8: =IF(SUMIFS('Trade Log'!$S$4:$S$153,'Trade Log'!$G$4:$G$153,"Yes",'Trade Log'!$S$4:$S$153,"<0")=0,"-",IFERROR(SUMIFS('Trade Log'!$S$4:$S$153,'Trade Log'!$G$4:$G$153,"Yes",'Trade Log'!$S$4:$S$153,">0")/-SUMIFS('Trade Log'!$S$4:$S$153,'Trade Log'!$G$4:$G$153,"Yes",'Trade Log'!$S$4:$S$153,"<0"),0)) -> - | M8: =IFERROR(COUNTIFS('Trade Log'!$G$4:$G$153,"Yes",'Trade Log'!$M$4:$M$153,"Yes")/COUNTIFS('Trade Log'!$G$4:$G$153,"Yes",'Trade Log'!$T$4:$T$153,"<>"),0) -> 1
A11: TRADES TAKEN | D11: SKIPPED | G11: AVG LEVERAGE | J11: LIQ BUFFER < 3x | M11: TO 30 TRADES
A12: =COUNTIFS('Trade Log'!$G$4:$G$153,"Yes",'Trade Log'!$T$4:$T$153,"<>") -> 1 | D12: =COUNTIF('Trade Log'!$G$4:$G$153,"No") -> 0 | G12: =IFERROR(AVERAGEIFS('Trade Log'!$L$4:$L$153,'Trade Log'!$G$4:$G$153,"Yes",'Trade Log'!$L$4:$L$153,">0"),0) -> 3 | J12: =COUNTIFS('Trade Log'!$G$4:$G$153,"Yes",'Trade Log'!$U$4:$U$153,">0",'Trade Log'!$U$4:$U$153,"<3") -> 0 | M12: =MAX(0,30-COUNTIFS('Trade Log'!$G$4:$G$153,"Yes",'Trade Log'!$T$4:$T$153,"<>")) -> 29
A42: Until 30 trades are logged, every number above is noise. Fill the log, do not act on it yet.

Sheet Trade Log
A1: TRADE LOG - one row per opportunity, taken or not
A2: ALWAYS FILL | H2: IF TAKEN | N2: CALIBRATION (30 sec, this is what tunes your rules) | R2: AUTO
A3: Date | B3: Time UTC | C3: Symbol | D3: Setup | E3: Grade | F3: Dir | G3: Taken? | H3: Entry | I3: Stop | J3: Exit | K3: Qty | L3: Leverage | M3: Followed plan? | N3: Pen. ATR | O3: Candles to reclaim | P3: OI confirmed? | Q3: Note / why skipped | R3: Risk $ | S3: Net P&L | T3: R | U3: Liq buffer
A4: 46273 | B4: 14:15 | C4: BTCUSDT | D4: Spring | E4: A | F4: Long | G4: Yes | H4: 95240 | I4: 94810 | J4: 96100 | K4: 1.16 | L4: 3 | M4: Yes | N4: 0.42 | O4: 2 | P4: Yes | Q4: EXAMPLE ROW - clear it. Reclaimed 4h swing low, OI dropped 1.8% on the reclaim. | R4: =IF(OR($G4<>"Yes",$H4="",$I4="",$K4=""),"",ABS($H4-$I4)*$K4) -> 498.8 | S4: =IF(OR($G4<>"Yes",$H4="",$J4="",$K4=""),"",IF($F4="Short",$H4-$J4,$J4-$H4)*$K4-($H4+$J4)*$K4*Dashboard!$D$5/100) -> 875.52508 | T4: =IF(OR($S4="",$R4="",$R4=0),"",$S4/$R4) -> 1.7552628 | U4: =IF(OR($L4="",$L4=0,$H4="",$I4=""),"",((100/$L4)-1)/(ABS($H4-$I4)/$H4*100)) -> 71.614574 | V4: =IFERROR(VALUE(LEFT($B4,2)),"") -> 14
R5: =IF(OR($G5<>"Yes",$H5="",$I5="",$K5=""),"",ABS($H5-$I5)*$K5) | S5: =IF(OR($G5<>"Yes",$H5="",$J5="",$K5=""),"",IF($F5="Short",$H5-$J5,$J5-$H5)*$K5-($H5+$J5)*$K5*Dashboard!$D$5/100) | T5: =IF(OR($S5="",$R5="",$R5=0),"",$S5/$R5) | U5: =IF(OR($L5="",$L5=0,$H5="",$I5=""),"",((100/$L5)-1)/(ABS($H5-$I5)/$H5*100)) | V5: =IFERROR(VALUE(LEFT($B5,2)),"")
R6: =IF(OR($G6<>"Yes",$H6="",$I6="",$K6=""),"",ABS($H6-$I6)*$K6) | S6: =IF(OR($G6<>"Yes",$H6="",$J6="",$K6=""),"",IF($F6="Short",$H6-$J6,$J6-$H6)*$K6-($H6+$J6)*$K6*Dashboard!$D$5/100) | T6: =IF(OR($S6="",$R6="",$R6=0),"",$S6/$R6) | U6: =IF(OR($L6="",$L6=0,$H6="",$I6=""),"",((100/$L6)-1)/(ABS($H6-$I6)/$H6*100)) | V6: =IFERROR(VALUE(LEFT($B6,2)),"")
R7: =IF(OR($G7<>"Yes",$H7="",$I7="",$K7=""),"",ABS($H7-$I7)*$K7) | S7: =IF(OR($G7<>"Yes",$H7="",$J7="",$K7=""),"",IF($F7="Short",$H7-$J7,$J7-$H7)*$K7-($H7+$J7)*$K7*Dashboard!$D$5/100) | T7: =IF(OR($S7="",$R7="",$R7=0),"",$S7/$R7) | U7: =IF(OR($L7="",$L7=0,$H7="",$I7=""),"",((100/$L7)-1)/(ABS($H7-$I7)/$H7*100)) | V7: =IFERROR(VALUE(LEFT($B7,2)),"")
R8: =IF(OR($G8<>"Yes",$H8="",$I8="",$K8=""),"",ABS($H8-$I8)*$K8) | S8: =IF(OR($G8<>"Yes",$H8="",$J8="",$K8=""),"",IF($F8="Short",$H8-$J8,$J8-$H8)*$K8-($H8+$J8)*$K8*Dashboard!$D$5/100) | T8: =IF(OR($S8="",$R8="",$R8=0),"",$S8/$R8) | U8: =IF(OR($L8="",$L8=0,$H8="",$I8=""),"",((100/$L8)-1)/(ABS($H8-$I8)/$H8*100)) | V8: =IFERROR(VALUE(LEFT($B8,2)),"")
R9: =IF(OR($G9<>"Yes",$H9="",$I9="",$K9=""),"",ABS($H9-$I9)*$K9) | S9: =IF(OR($G9<>"Yes",$H9="",$J9="",$K9=""),"",IF($F9="Short",$H9-$J9,$J9-$H9)*$K9-($H9+$J9)*$K9*Dashboard!$D$5/100) | T9: =IF(OR($S9="",$R9="",$R9=0),"",$S9/$R9) | U9: =IF(OR($L9="",$L9=0,$H9="",$I9=""),"",((100/$L9)-1)/(ABS($H9-$I9)/$H9*100)) | V9: =IFERROR(VALUE(LEFT($B9,2)),"")
R10: =IF(OR($G10<>"Yes",$H10="",$I10="",$K10=""),"",ABS($H10-$I10)*$K10) | S10: =IF(OR($G10<>"Yes",$H10="",$J10="",$K10=""),"",IF($F10="Short",$H10-$J10,$J10-$H10)*$K10-($H10+$J10)*$K10*Dashboard!$D$5/100) | T10: =IF(OR($S10="",$R10="",$R10=0),"",$S10/$R10) | U10: =IF(OR($L10="",$L10=0,$H10="",$I10=""),"",((100/$L10)-1)/(ABS($H10-$I10)/$H10*100)) | V10: =IFERROR(VALUE(LEFT($B10,2)),"")
R11: =IF(OR($G11<>"Yes",$H11="",$I11="",$K11=""),"",ABS($H11-$I11)*$K11) | S11: =IF(OR($G11<>"Yes",$H11="",$J11="",$K11=""),"",IF($F11="Short",$H11-$J11,$J11-$H11)*$K11-($H11+$J11)*$K11*Dashboard!$D$5/100) | T11: =IF(OR($S11="",$R11="",$R11=0),"",$S11/$R11) | U11: =IF(OR($L11="",$L11=0,$H11="",$I11=""),"",((100/$L11)-1)/(ABS($H11-$I11)/$H11*100)) | V11: =IFERROR(VALUE(LEFT($B11,2)),"")
R12: =IF(OR($G12<>"Yes",$H12="",$I12="",$K12=""),"",ABS($H12-$I12)*$K12) | S12: =IF(OR($G12<>"Yes",$H12="",$J12="",$K12=""),"",IF($F12="Short",$H12-$J12,$J12-$H12)*$K12-($H12+$J12)*$K12*Dashboard!$D$5/100) | T12: =IF(OR($S12="",$R12="",$R12=0),"",$S12/$R12) | U12: =IF(OR($L12="",$L12=0,$H12="",$I12=""),"",((100/$L12)-1)/(ABS($H12-$I12)/$H12*100)) | V12: =IFERROR(VALUE(LEFT($B12,2)),"")
R13: =IF(OR($G13<>"Yes",$H13="",$I13="",$K13=""),"",ABS($H13-$I13)*$K13) | S13: =IF(OR($G13<>"Yes",$H13="",$J13="",$K13=""),"",IF($F13="Short",$H13-$J13,$J13-$H13)*$K13-($H13+$J13)*$K13*Dashboard!$D$5/100) | T13: =IF(OR($S13="",$R13="",$R13=0),"",$S13/$R13) | U13: =IF(OR($L13="",$L13=0,$H13="",$I13=""),"",((100/$L13)-1)/(ABS($H13-$I13)/$H13*100)) | V13: =IFERROR(VALUE(LEFT($B13,2)),"")
R14: =IF(OR($G14<>"Yes",$H14="",$I14="",$K14=""),"",ABS($H14-$I14)*$K14) | S14: =IF(OR($G14<>"Yes",$H14="",$J14="",$K14=""),"",IF($F14="Short",$H14-$J14,$J14-$H14)*$K14-($H14+$J14)*$K14*Dashboard!$D$5/100) | T14: =IF(OR($S14="",$R14="",$R14=0),"",$S14/$R14) | U14: =IF(OR($L14="",$L14=0,$H14="",$I14=""),"",((100/$L14)-1)/(ABS($H14-$I14)/$H14*100)) | V14: =IFERROR(VALUE(LEFT($B14,2)),"")
R15: =IF(OR($G15<>"Yes",$H15="",$I15="",$K15=""),"",ABS($H15-$I15)*$K15) | S15: =IF(OR($G15<>"Yes",$H15="",$J15="",$K15=""),"",IF($F15="Short",$H15-$J15,$J15-$H15)*$K15-($H15+$J15)*$K15*Dashboard!$D$5/100) | T15: =IF(OR($S15="",$R15="",$R15=0),"",$S15/$R15) | U15: =IF(OR($L15="",$L15=0,$H15="",$I15=""),"",((100/$L15)-1)/(ABS($H15-$I15)/$H15*100)) | V15: =IFERROR(VALUE(LEFT($B15,2)),"")
R16: =IF(OR($G16<>"Yes",$H16="",$I16="",$K16=""),"",ABS($H16-$I16)*$K16) | S16: =IF(OR($G16<>"Yes",$H16="",$J16="",$K16=""),"",IF($F16="Short",$H16-$J16,$J16-$H16)*$K16-($H16+$J16)*$K16*Dashboard!$D$5/100) | T16: =IF(OR($S16="",$R16="",$R16=0),"",$S16/$R16) | U16: =IF(OR($L16="",$L16=0,$H16="",$I16=""),"",((100/$L16)-1)/(ABS($H16-$I16)/$H16*100)) | V16: =IFERROR(VALUE(LEFT($B16,2)),"")
... R153: =IF(OR($G153<>"Yes",$H153="",$I153="",$K153=""),"",ABS($H153-$I153)*$K153) | S153: =IF(OR($G153<>"Yes",$H153="",$J153="",$K153=""),"",IF($F153="Short",$H153-$J153,$J153-$H153)*$K153-($H153+$J153)*$K153*Dashboard!$D$5/100) | T153: =IF(OR($S153="",$R153="",$R153=0),"",$S153/$R153) | U153: =IF(OR($L153="",$L153=0,$H153="",$I153=""),"",((100/$L153)-1)/(ABS($H153-$I153)/$H153*100)) | V153: =IFERROR(VALUE(LEFT($B153,2)),"")

Sheet Diagnostics
A1: DIAGNOSTICS - the questions your log exists to answer
A2: Every threshold in the checklist is a guess until this sheet says otherwise. Read it after 30 trades, not before.
A4: 1. DOES THE GRADE MEAN ANYTHING?
A5: If A grades and C grades produce the same avg R, the rubric measures nothing and needs rebuilding.
C6: n | E6: avg R | G6: net $ | I6: verdict
A7: Grade A | C7: =COUNTIFS('Trade Log'!$G$4:$G$153,"Yes",'Trade Log'!$T$4:$T$153,"<>",'Trade Log'!$E$4:$E$153,"A") -> 1 | E7: =IFERROR(AVERAGEIFS('Trade Log'!$T$4:$T$153,'Trade Log'!$G$4:$G$153,"Yes",'Trade Log'!$T$4:$T$153,"<>",'Trade Log'!$E$4:$E$153,"A"),0) -> 1.7552628 | G7: =SUMIFS('Trade Log'!$S$4:$S$153,'Trade Log'!$G$4:$G$153,"Yes",'Trade Log'!$E$4:$E$153,"A") -> 875.52508 | I7: Want a clean descending ladder A to D
A8: Grade B | C8: =COUNTIFS('Trade Log'!$G$4:$G$153,"Yes",'Trade Log'!$T$4:$T$153,"<>",'Trade Log'!$E$4:$E$153,"B") -> 0 | E8: =IFERROR(AVERAGEIFS('Trade Log'!$T$4:$T$153,'Trade Log'!$G$4:$G$153,"Yes",'Trade Log'!$T$4:$T$153,"<>",'Trade Log'!$E$4:$E$153,"B"),0) -> 0 | G8: =SUMIFS('Trade Log'!$S$4:$S$153,'Trade Log'!$G$4:$G$153,"Yes",'Trade Log'!$E$4:$E$153,"B") -> 0
A9: Grade C | C9: =COUNTIFS('Trade Log'!$G$4:$G$153,"Yes",'Trade Log'!$T$4:$T$153,"<>",'Trade Log'!$E$4:$E$153,"C") -> 0 | E9: =IFERROR(AVERAGEIFS('Trade Log'!$T$4:$T$153,'Trade Log'!$G$4:$G$153,"Yes",'Trade Log'!$T$4:$T$153,"<>",'Trade Log'!$E$4:$E$153,"C"),0) -> 0 | G9: =SUMIFS('Trade Log'!$S$4:$S$153,'Trade Log'!$G$4:$G$153,"Yes",'Trade Log'!$E$4:$E$153,"C") -> 0
A10: Grade D | C10: =COUNTIFS('Trade Log'!$G$4:$G$153,"Yes",'Trade Log'!$T$4:$T$153,"<>",'Trade Log'!$E$4:$E$153,"D") -> 0 | E10: =IFERROR(AVERAGEIFS('Trade Log'!$T$4:$T$153,'Trade Log'!$G$4:$G$153,"Yes",'Trade Log'!$T$4:$T$153,"<>",'Trade Log'!$E$4:$E$153,"D"),0) -> 0 | G10: =SUMIFS('Trade Log'!$S$4:$S$153,'Trade Log'!$G$4:$G$153,"Yes",'Trade Log'!$E$4:$E$153,"D") -> 0
A12: 2. WHICH SETUP ACTUALLY WORKS?
A13: Expect one or two to carry the book. Stop trading the ones that do not.
C14: n | E14: avg R | G14: net $ | I14: verdict
A15: Spring | C15: =COUNTIFS('Trade Log'!$G$4:$G$153,"Yes",'Trade Log'!$T$4:$T$153,"<>",'Trade Log'!$D$4:$D$153,"Spring") -> 1 | E15: =IFERROR(AVERAGEIFS('Trade Log'!$T$4:$T$153,'Trade Log'!$G$4:$G$153,"Yes",'Trade Log'!$T$4:$T$153,"<>",'Trade Log'!$D$4:$D$153,"Spring"),0) -> 1.7552628 | G15: =SUMIFS('Trade Log'!$S$4:$S$153,'Trade Log'!$G$4:$G$153,"Yes",'Trade Log'!$D$4:$D$153,"Spring") -> 875.52508 | I15: Below 10 trades this is noise
A16: Upthrust | C16: =COUNTIFS('Trade Log'!$G$4:$G$153,"Yes",'Trade Log'!$T$4:$T$153,"<>",'Trade Log'!$D$4:$D$153,"Upthrust") -> 0 | E16: =IFERROR(AVERAGEIFS('Trade Log'!$T$4:$T$153,'Trade Log'!$G$4:$G$153,"Yes",'Trade Log'!$T$4:$T$153,"<>",'Trade Log'!$D$4:$D$153,"Upthrust"),0) -> 0 | G16: =SUMIFS('Trade Log'!$S$4:$S$153,'Trade Log'!$G$4:$G$153,"Yes",'Trade Log'!$D$4:$D$153,"Upthrust") -> 0
A17: Sweep | C17: =COUNTIFS('Trade Log'!$G$4:$G$153,"Yes",'Trade Log'!$T$4:$T$153,"<>",'Trade Log'!$D$4:$D$153,"Sweep") -> 0 | E17: =IFERROR(AVERAGEIFS('Trade Log'!$T$4:$T$153,'Trade Log'!$G$4:$G$153,"Yes",'Trade Log'!$T$4:$T$153,"<>",'Trade Log'!$D$4:$D$153,"Sweep"),0) -> 0 | G17: =SUMIFS('Trade Log'!$S$4:$S$153,'Trade Log'!$G$4:$G$153,"Yes",'Trade Log'!$D$4:$D$153,"Sweep") -> 0
A18: Failed retest | C18: =COUNTIFS('Trade Log'!$G$4:$G$153,"Yes",'Trade Log'!$T$4:$T$153,"<>",'Trade Log'!$D$4:$D$153,"Failed retest") -> 0 | E18: =IFERROR(AVERAGEIFS('Trade Log'!$T$4:$T$153,'Trade Log'!$G$4:$G$153,"Yes",'Trade Log'!$T$4:$T$153,"<>",'Trade Log'!$D$4:$D$153,"Failed retest"),0) -> 0 | G18: =SUMIFS('Trade Log'!$S$4:$S$153,'Trade Log'!$G$4:$G$153,"Yes",'Trade Log'!$D$4:$D$153,"Failed retest") -> 0
A20: 3. ARE THE THIN HOURS COSTING YOU?
A21: 03:00 to 07:00 UTC produces sweeps that reverse and then continue. If this is negative, stop trading it.
C22: n | E22: avg R | G22: net $ | I22: verdict
A23: Thin hours 03-07 UTC | C23: =COUNTIFS('Trade Log'!$G$4:$G$153,"Yes",'Trade Log'!$T$4:$T$153,"<>",'Trade Log'!$V$4:$V$153,">=3",'Trade Log'!$V$4:$V$153,"<7") -> 0 | E23: =IFERROR(AVERAGEIFS('Trade Log'!$T$4:$T$153,'Trade Log'!$G$4:$G$153,"Yes",'Trade Log'!$T$4:$T$153,"<>",'Trade Log'!$V$4:$V$153,">=3",'Trade Log'!$V$4:$V$153,"<7"),0) -> 0 | G23: =SUMIFS('Trade Log'!$S$4:$S$153,'Trade Log'!$G$4:$G$153,"Yes",'Trade Log'!$V$4:$V$153,">=3",'Trade Log'!$V$4:$V$153,"<7") -> 0 | I23: Negative here means block the window outright
A24: All other hours | C24: =COUNTIFS('Trade Log'!$G$4:$G$153,"Yes",'Trade Log'!$T$4:$T$153,"<>",'Trade Log'!$V$4:$V$153,">=7") -> 1 | E24: =IFERROR(AVERAGEIFS('Trade Log'!$T$4:$T$153,'Trade Log'!$G$4:$G$153,"Yes",'Trade Log'!$T$4:$T$153,"<>",'Trade Log'!$V$4:$V$153,">=7"),0) -> 1.7552628 | G24: =SUMIFS('Trade Log'!$S$4:$S$153,'Trade Log'!$G$4:$G$153,"Yes",'Trade Log'!$V$4:$V$153,">=7") -> 875.52508
A26: 4. IS THE PENETRATION FLOOR RIGHT?
A27: Floor is 0.25 ATR, abandon is 1.0. If losers cluster below 0.25, raise it. If winners appear above 1.0, widen it.
C28: n | E28: avg R | G28: net $ | I28: verdict
A29: Under 0.25 ATR | C29: =COUNTIFS('Trade Log'!$G$4:$G$153,"Yes",'Trade Log'!$T$4:$T$153,"<>",'Trade Log'!$N$4:$N$153,">=0",'Trade Log'!$N$4:$N$153,"<0.25") -> 0 | E29: =IFERROR(AVERAGEIFS('Trade Log'!$T$4:$T$153,'Trade Log'!$G$4:$G$153,"Yes",'Trade Log'!$T$4:$T$153,"<>",'Trade Log'!$N$4:$N$153,">=0",'Trade Log'!$N$4:$N$153,"<0.25"),0) -> 0 | G29: =SUMIFS('Trade Log'!$S$4:$S$153,'Trade Log'!$G$4:$G$153,"Yes",'Trade Log'!$N$4:$N$153,">=0",'Trade Log'!$N$4:$N$153,"<0.25") -> 0
A30: 0.25 to 0.60 | C30: =COUNTIFS('Trade Log'!$G$4:$G$153,"Yes",'Trade Log'!$T$4:$T$153,"<>",'Trade Log'!$N$4:$N$153,">=0.25",'Trade Log'!$N$4:$N$153,"<0.6") -> 1 | E30: =IFERROR(AVERAGEIFS('Trade Log'!$T$4:$T$153,'Trade Log'!$G$4:$G$153,"Yes",'Trade Log'!$T$4:$T$153,"<>",'Trade Log'!$N$4:$N$153,">=0.25",'Trade Log'!$N$4:$N$153,"<0.6"),0) -> 1.7552628 | G30: =SUMIFS('Trade Log'!$S$4:$S$153,'Trade Log'!$G$4:$G$153,"Yes",'Trade Log'!$N$4:$N$153,">=0.25",'Trade Log'!$N$4:$N$153,"<0.6") -> 875.52508
A31: 0.60 to 1.00 | C31: =COUNTIFS('Trade Log'!$G$4:$G$153,"Yes",'Trade Log'!$T$4:$T$153,"<>",'Trade Log'!$N$4:$N$153,">=0.6",'Trade Log'!$N$4:$N$153,"<1.0") -> 0 | E31: =IFERROR(AVERAGEIFS('Trade Log'!$T$4:$T$153,'Trade Log'!$G$4:$G$153,"Yes",'Trade Log'!$T$4:$T$153,"<>",'Trade Log'!$N$4:$N$153,">=0.6",'Trade Log'!$N$4:$N$153,"<1.0"),0) -> 0 | G31: =SUMIFS('Trade Log'!$S$4:$S$153,'Trade Log'!$G$4:$G$153,"Yes",'Trade Log'!$N$4:$N$153,">=0.6",'Trade Log'!$N$4:$N$153,"<1.0") -> 0
A32: Over 1.00 ATR | C32: =COUNTIFS('Trade Log'!$G$4:$G$153,"Yes",'Trade Log'!$T$4:$T$153,"<>",'Trade Log'!$N$4:$N$153,">=1.0",'Trade Log'!$N$4:$N$153,"<99") -> 0 | E32: =IFERROR(AVERAGEIFS('Trade Log'!$T$4:$T$153,'Trade Log'!$G$4:$G$153,"Yes",'Trade Log'!$T$4:$T$153,"<>",'Trade Log'!$N$4:$N$153,">=1.0",'Trade Log'!$N$4:$N$153,"<99"),0) -> 0 | G32: =SUMIFS('Trade Log'!$S$4:$S$153,'Trade Log'!$G$4:$G$153,"Yes",'Trade Log'!$N$4:$N$153,">=1.0",'Trade Log'!$N$4:$N$153,"<99") -> 0
A34: 5. IS THE TWO TO FOUR CANDLE WINDOW RIGHT?
A35: If winners cluster at 1 to 3 candles, tighten the window. If they appear at 5 plus, widen it.
C36: n | E36: avg R | G36: net $ | I36: verdict
A37: 1 to 2 candles | C37: =COUNTIFS('Trade Log'!$G$4:$G$153,"Yes",'Trade Log'!$T$4:$T$153,"<>",'Trade Log'!$O$4:$O$153,">=1",'Trade Log'!$O$4:$O$153,"<3") -> 1 | E37: =IFERROR(AVERAGEIFS('Trade Log'!$T$4:$T$153,'Trade Log'!$G$4:$G$153,"Yes",'Trade Log'!$T$4:$T$153,"<>",'Trade Log'!$O$4:$O$153,">=1",'Trade Log'!$O$4:$O$153,"<3"),0) -> 1.7552628 | G37: =SUMIFS('Trade Log'!$S$4:$S$153,'Trade Log'!$G$4:$G$153,"Yes",'Trade Log'!$O$4:$O$153,">=1",'Trade Log'!$O$4:$O$153,"<3") -> 875.52508
A38: 3 to 4 candles | C38: =COUNTIFS('Trade Log'!$G$4:$G$153,"Yes",'Trade Log'!$T$4:$T$153,"<>",'Trade Log'!$O$4:$O$153,">=3",'Trade Log'!$O$4:$O$153,"<5") -> 0 | E38: =IFERROR(AVERAGEIFS('Trade Log'!$T$4:$T$153,'Trade Log'!$G$4:$G$153,"Yes",'Trade Log'!$T$4:$T$153,"<>",'Trade Log'!$O$4:$O$153,">=3",'Trade Log'!$O$4:$O$153,"<5"),0) -> 0 | G38: =SUMIFS('Trade Log'!$S$4:$S$153,'Trade Log'!$G$4:$G$153,"Yes",'Trade Log'!$O$4:$O$153,">=3",'Trade Log'!$O$4:$O$153,"<5") -> 0
A39: 5 or more | C39: =COUNTIFS('Trade Log'!$G$4:$G$153,"Yes",'Trade Log'!$T$4:$T$153,"<>",'Trade Log'!$O$4:$O$153,">=5",'Trade Log'!$O$4:$O$153,"<99") -> 0 | E39: =IFERROR(AVERAGEIFS('Trade Log'!$T$4:$T$153,'Trade Log'!$G$4:$G$153,"Yes",'Trade Log'!$T$4:$T$153,"<>",'Trade Log'!$O$4:$O$153,">=5",'Trade Log'!$O$4:$O$153,"<99"),0) -> 0 | G39: =SUMIFS('Trade Log'!$S$4:$S$153,'Trade Log'!$G$4:$G$153,"Yes",'Trade Log'!$O$4:$O$153,">=5",'Trade Log'!$O$4:$O$153,"<99") -> 0
A41: 6. DOES OPEN INTEREST CONFIRMATION MATTER?
A42: If these two are the same, drop the check and save yourself the step.
C43: n | E43: avg R | G43: net $ | I43: verdict
A44: OI confirmed | C44: =COUNTIFS('Trade Log'!$G$4:$G$153,"Yes",'Trade Log'!$T$4:$T$153,"<>",'Trade Log'!$P$4:$P$153,"Yes") -> 1 | E44: =IFERROR(AVERAGEIFS('Trade Log'!$T$4:$T$153,'Trade Log'!$G$4:$G$153,"Yes",'Trade Log'!$T$4:$T$153,"<>",'Trade Log'!$P$4:$P$153,"Yes"),0) -> 1.7552628 | G44: =SUMIFS('Trade Log'!$S$4:$S$153,'Trade Log'!$G$4:$G$153,"Yes",'Trade Log'!$P$4:$P$153,"Yes") -> 875.52508
A45: OI not confirmed | C45: =COUNTIFS('Trade Log'!$G$4:$G$153,"Yes",'Trade Log'!$T$4:$T$153,"<>",'Trade Log'!$P$4:$P$153,"No") -> 0 | E45: =IFERROR(AVERAGEIFS('Trade Log'!$T$4:$T$153,'Trade Log'!$G$4:$G$153,"Yes",'Trade Log'!$T$4:$T$153,"<>",'Trade Log'!$P$4:$P$153,"No"),0) -> 0 | G45: =SUMIFS('Trade Log'!$S$4:$S$153,'Trade Log'!$G$4:$G$153,"Yes",'Trade Log'!$P$4:$P$153,"No") -> 0
A47: 7. IS THE PROBLEM THE SETUP OR YOU?
A48: If in-plan trades are profitable and out-of-plan are not, the strategy is fine and discipline is the issue.
C49: n | E49: avg R | G49: net $ | I49: verdict
A50: Followed the plan | C50: =COUNTIFS('Trade Log'!$G$4:$G$153,"Yes",'Trade Log'!$T$4:$T$153,"<>",'Trade Log'!$M$4:$M$153,"Yes") -> 1 | E50: =IFERROR(AVERAGEIFS('Trade Log'!$T$4:$T$153,'Trade Log'!$G$4:$G$153,"Yes",'Trade Log'!$T$4:$T$153,"<>",'Trade Log'!$M$4:$M$153,"Yes"),0) -> 1.7552628 | G50: =SUMIFS('Trade Log'!$S$4:$S$153,'Trade Log'!$G$4:$G$153,"Yes",'Trade Log'!$M$4:$M$153,"Yes") -> 875.52508
A51: Did not follow the plan | C51: =COUNTIFS('Trade Log'!$G$4:$G$153,"Yes",'Trade Log'!$T$4:$T$153,"<>",'Trade Log'!$M$4:$M$153,"No") -> 0 | E51: =IFERROR(AVERAGEIFS('Trade Log'!$T$4:$T$153,'Trade Log'!$G$4:$G$153,"Yes",'Trade Log'!$T$4:$T$153,"<>",'Trade Log'!$M$4:$M$153,"No"),0) -> 0 | G51: =SUMIFS('Trade Log'!$S$4:$S$153,'Trade Log'!$G$4:$G$153,"Yes",'Trade Log'!$M$4:$M$153,"No") -> 0
A53: 8. IS LEVERAGE HURTING YOU?
A54: Leverage never changes R. It only moves your liquidation price closer to your stop. If the high leverage rows underperform, you are being liquidated on trades that were not wrong.
C55: n | E55: avg R | G55: net $ | I55: verdict
A56: 1x to 2x | C56: =COUNTIFS('Trade Log'!$G$4:$G$153,"Yes",'Trade Log'!$T$4:$T$153,"<>",'Trade Log'!$L$4:$L$153,">=1",'Trade Log'!$L$4:$L$153,"<3") -> 0 | E56: =IFERROR(AVERAGEIFS('Trade Log'!$T$4:$T$153,'Trade Log'!$G$4:$G$153,"Yes",'Trade Log'!$T$4:$T$153,"<>",'Trade Log'!$L$4:$L$153,">=1",'Trade Log'!$L$4:$L$153,"<3"),0) -> 0 | G56: =SUMIFS('Trade Log'!$S$4:$S$153,'Trade Log'!$G$4:$G$153,"Yes",'Trade Log'!$L$4:$L$153,">=1",'Trade Log'!$L$4:$L$153,"<3") -> 0 | I56: Required leverage = risk% / stop%. Above that is unused.
A57: 3x to 5x | C57: =COUNTIFS('Trade Log'!$G$4:$G$153,"Yes",'Trade Log'!$T$4:$T$153,"<>",'Trade Log'!$L$4:$L$153,">=3",'Trade Log'!$L$4:$L$153,"<6") -> 1 | E57: =IFERROR(AVERAGEIFS('Trade Log'!$T$4:$T$153,'Trade Log'!$G$4:$G$153,"Yes",'Trade Log'!$T$4:$T$153,"<>",'Trade Log'!$L$4:$L$153,">=3",'Trade Log'!$L$4:$L$153,"<6"),0) -> 1.7552628 | G57: =SUMIFS('Trade Log'!$S$4:$S$153,'Trade Log'!$G$4:$G$153,"Yes",'Trade Log'!$L$4:$L$153,">=3",'Trade Log'!$L$4:$L$153,"<6") -> 875.52508
A58: 6x to 10x | C58: =COUNTIFS('Trade Log'!$G$4:$G$153,"Yes",'Trade Log'!$T$4:$T$153,"<>",'Trade Log'!$L$4:$L$153,">=6",'Trade Log'!$L$4:$L$153,"<11") -> 0 | E58: =IFERROR(AVERAGEIFS('Trade Log'!$T$4:$T$153,'Trade Log'!$G$4:$G$153,"Yes",'Trade Log'!$T$4:$T$153,"<>",'Trade Log'!$L$4:$L$153,">=6",'Trade Log'!$L$4:$L$153,"<11"),0) -> 0 | G58: =SUMIFS('Trade Log'!$S$4:$S$153,'Trade Log'!$G$4:$G$153,"Yes",'Trade Log'!$L$4:$L$153,">=6",'Trade Log'!$L$4:$L$153,"<11") -> 0
A59: Over 10x | C59: =COUNTIFS('Trade Log'!$G$4:$G$153,"Yes",'Trade Log'!$T$4:$T$153,"<>",'Trade Log'!$L$4:$L$153,">=11",'Trade Log'!$L$4:$L$153,"<999") -> 0 | E59: =IFERROR(AVERAGEIFS('Trade Log'!$T$4:$T$153,'Trade Log'!$G$4:$G$153,"Yes",'Trade Log'!$T$4:$T$153,"<>",'Trade Log'!$L$4:$L$153,">=11",'Trade Log'!$L$4:$L$153,"<999"),0) -> 0 | G59: =SUMIFS('Trade Log'!$S$4:$S$153,'Trade Log'!$G$4:$G$153,"Yes",'Trade Log'!$L$4:$L$153,">=11",'Trade Log'!$L$4:$L$153,"<999") -> 0

Sheet Playbook
A1: PLAYBOOK - if it is not on this page, it is not a trade
A3: RISK RULES
A4: 1. | B4: Risk 1% of equity per trade. Size comes from the stop, never the other way round.
A5: 2. | B5: Stop goes a few ticks beyond the trap's extreme wick, not beyond the level.
A6: 3. | B6: Liquidation must sit at least 3 stop widths away. Check the Liq buffer column before sending.
A7: 4. | B7: Required leverage is risk% divided by stop%. Anything above that is unused risk.
A8: 5. | B8: Entry is the decisive CLOSE back inside. Never the wick.
A9: 6. | B9: No expansion by candle four: exit at breakeven. Rule, not judgment.
A10: 7. | B10: Never move a stop away from entry.
A11: 8. | B11: Both gates must pass: range 6x ATR and 4x the stop, cost under 10% of risk.
A12: 9. | B12: Middle third of the range: no trade.
A13: 10. | B13: Three losses in a day: stop for the day.
A14: 11. | B14: Rule changes happen at the monthly review, never during a session.
A15: 12. | B15: Log within 10 minutes, win or lose, taken or skipped.
A18: THE FOUR SETUPS (edit the trigger and invalidation in your own words)
A19: Setup | C19: Entry trigger | E19: Invalidation | G19: Target | I19: Notes
A20: Spring | C20: Close back above the range low after a break | E20: Below the sweep wick | G20: Range high
A21: Upthrust | C21: Close back below the range high after a break | E21: Above the trap wick | G21: Range low
A22: Sweep | C22: Wick through the level, close back inside, OI drops | E22: Beyond the sweep wick | G22: Prior swing
A23: Failed retest | C23: Retest of a broken level closes back through | E23: Beyond the retest extreme | G23: Prior range

Sheet Calc
A1: n | B1: cum | C1: equity
A2: =IF('Trade Log'!T4="","",'Trade Log'!A4) -> 46273 | B2: =IF('Trade Log'!S4="",0,'Trade Log'!S4) -> 875.52508 | C2: =Dashboard!$B$4+B2 -> 50875.525
A3: =IF('Trade Log'!T5="","",'Trade Log'!A5) | B3: =IF('Trade Log'!S5="",N(B2),N(B2)+'Trade Log'!S5) -> 875.52508 | C3: =Dashboard!$B$4+B3 -> 50875.525
A4: =IF('Trade Log'!T6="","",'Trade Log'!A6) | B4: =IF('Trade Log'!S6="",N(B3),N(B3)+'Trade Log'!S6) -> 875.52508 | C4: =Dashboard!$B$4+B4 -> 50875.525
A5: =IF('Trade Log'!T7="","",'Trade Log'!A7) | B5: =IF('Trade Log'!S7="",N(B4),N(B4)+'Trade Log'!S7) -> 875.52508 | C5: =Dashboard!$B$4+B5 -> 50875.525
A6: =IF('Trade Log'!T8="","",'Trade Log'!A8) | B6: =IF('Trade Log'!S8="",N(B5),N(B5)+'Trade Log'!S8) -> 875.52508 | C6: =Dashboard!$B$4+B6 -> 50875.525
A7: =IF('Trade Log'!T9="","",'Trade Log'!A9) | B7: =IF('Trade Log'!S9="",N(B6),N(B6)+'Trade Log'!S9) -> 875.52508 | C7: =Dashboard!$B$4+B7 -> 50875.525
A8: =IF('Trade Log'!T10="","",'Trade Log'!A10) | B8: =IF('Trade Log'!S10="",N(B7),N(B7)+'Trade Log'!S10) -> 875.52508 | C8: =Dashboard!$B$4+B8 -> 50875.525
A9: =IF('Trade Log'!T11="","",'Trade Log'!A11) | B9: =IF('Trade Log'!S11="",N(B8),N(B8)+'Trade Log'!S11) -> 875.52508 | C9: =Dashboard!$B$4+B9 -> 50875.525
A10: =IF('Trade Log'!T12="","",'Trade Log'!A12) | B10: =IF('Trade Log'!S12="",N(B9),N(B9)+'Trade Log'!S12) -> 875.52508 | C10: =Dashboard!$B$4+B10 -> 50875.525
A11: =IF('Trade Log'!T13="","",'Trade Log'!A13) | B11: =IF('Trade Log'!S13="",N(B10),N(B10)+'Trade Log'!S13) -> 875.52508 | C11: =Dashboard!$B$4+B11 -> 50875.525
A12: =IF('Trade Log'!T14="","",'Trade Log'!A14) | B12: =IF('Trade Log'!S14="",N(B11),N(B11)+'Trade Log'!S14) -> 875.52508 | C12: =Dashboard!$B$4+B12 -> 50875.525
A13: =IF('Trade Log'!T15="","",'Trade Log'!A15) | B13: =IF('Trade Log'!S15="",N(B12),N(B12)+'Trade Log'!S15) -> 875.52508 | C13: =Dashboard!$B$4+B13 -> 50875.525
A14: =IF('Trade Log'!T16="","",'Trade Log'!A16) | B14: =IF('Trade Log'!S16="",N(B13),N(B13)+'Trade Log'!S16) -> 875.52508 | C14: =Dashboard!$B$4+B14 -> 50875.525
... A151: =IF('Trade Log'!T153="","",'Trade Log'!A153) | B151: =IF('Trade Log'!S153="",N(B150),N(B150)+'Trade Log'!S153) -> 875.52508 | C151: =Dashboard!$B$4+B151 -> 50875.525
